Metadata-Version: 2.4
Name: dayamol_ai2
Version: 0.1.0
Summary: A simple AI helper library with text processing utilities.
Author-email: Mahadevan Nair <mahadevannair16@gmail.com>
Project-URL: Homepage, https://github.com/MahaDevan20/aimon
Keywords: ai,utilities,text,helpers
Classifier: Programming Language :: Python :: 3
Classifier: License :: OSI Approved :: MIT License
Classifier: Operating System :: OS Independent
Requires-Python: >=3.8
